rtml_tools/__init__.py
rtml_tools/config.py
rtml_tools/feature_store_api/__init__.py
rtml_tools/feature_store_api/api.py
rtml_tools/feature_store_api/demo.py
rtml_tools/feature_store_api/types.py
rtml_tools/kraken_api/__init__.py
rtml_tools/kraken_api/historical.py
rtml_tools/kraken_api/types.py
rtml_tools/kraken_api/websocket.py
rtml_tools/logging.py
rtml_tools/ml/predict.py
rtml_tools/ml/preprocessing.py
rtml_tools/ml/train.py
rtml_tools/quix_api/app_factory.py
rtml_tools/quix_api/producer_wrapper.py
rtml_tools-0.2.2.dist-info/METADATA
rtml_tools-0.2.2.dist-info/WHEEL
rtml_tools-0.2.2.dist-info/RECORD
