Metadata-Version: 2.1
Name: rtml-tools
Version: 0.2.2
Summary: 
Author: Paulescu
Author-email: plabartabajo@gmail.com
Requires-Python: >=3.10,<3.12
Classifier: Programming Language :: Python :: 3
Classifier: Programming Language :: Python :: 3.10
Classifier: Programming Language :: Python :: 3.11
Requires-Dist: hopsworks (>=3.4.4,<4.0.0)
Requires-Dist: pydantic (>=2.5.3,<3.0.0)
Requires-Dist: python-dotenv (>=1.0.1,<2.0.0)
Requires-Dist: pyyaml (>=6.0.1,<7.0.0)
Requires-Dist: quixstreams (>=2.0a)
